ansibledoctor/__init__.py
ansibledoctor/annotation.py
ansibledoctor/cli.py
ansibledoctor/config.py
ansibledoctor/constants.py
ansibledoctor/doc_generator.py
ansibledoctor/doc_parser.py
ansibledoctor/exception.py
ansibledoctor/file_registry.py
ansibledoctor/template.py
ansibledoctor/templates/hugo-book/_meta.j2
ansibledoctor/templates/hugo-book/_requirements.j2
ansibledoctor/templates/hugo-book/_tag.j2
ansibledoctor/templates/hugo-book/_toc.j2
ansibledoctor/templates/hugo-book/_todo.j2
ansibledoctor/templates/hugo-book/_vars.j2
ansibledoctor/templates/hugo-book/_vars_tabulated.j2
ansibledoctor/templates/hugo-book/index.md.j2
ansibledoctor/templates/readme/README.md.j2
ansibledoctor/templates/readme/_meta.j2
ansibledoctor/templates/readme/_requirements.j2
ansibledoctor/templates/readme/_tag.j2
ansibledoctor/templates/readme/_toc.j2
ansibledoctor/templates/readme/_todo.j2
ansibledoctor/templates/readme/_vars.j2
ansibledoctor/templates/readme/_vars_tabulated.j2
ansibledoctor/templates/readme-adoc/README.adoc.j2
ansibledoctor/templates/readme-adoc/_meta.j2
ansibledoctor/templates/readme-adoc/_requirements.j2
ansibledoctor/templates/readme-adoc/_tag.j2
ansibledoctor/templates/readme-adoc/_toc.j2
ansibledoctor/templates/readme-adoc/_todo.j2
ansibledoctor/templates/readme-adoc/_vars.j2
ansibledoctor/templates/readme-adoc/_vars_tabulated.j2
ansibledoctor/utils/__init__.py
ansibledoctor/utils/yaml_helper.py
ansible_doctor-8.2.0.dist-info/METADATA
ansible_doctor-8.2.0.dist-info/WHEEL
ansible_doctor-8.2.0.dist-info/entry_points.txt
ansible_doctor-8.2.0.dist-info/licenses/LICENSE
ansible_doctor-8.2.0.dist-info/RECORD
