Metadata-Version: 2.4
Name: ansible-doctor
Version: 8.2.0
Summary: Generate documentation from annotated Ansible roles using templates.
License: GPL-3.0-only
License-File: LICENSE
Keywords: ansible,role,documentation
Author: Robert Kaussow
Author-email: mail@thegeeklab.de
Requires-Python: >=3.11.0,<4.0.0
Classifier: Development Status :: 5 - Production/Stable
Classifier: Environment :: Console
Classifier: Intended Audience :: Developers
Classifier: Intended Audience :: Information Technology
Classifier: Intended Audience :: System Administrators
Classifier: License :: OSI Approved :: GNU General Public License v3 (GPLv3)
Classifier: Natural Language :: English
Classifier: Operating System :: POSIX
Classifier: Programming Language :: Python :: 3
Classifier: Programming Language :: Python :: 3.11
Classifier: Programming Language :: Python :: 3.12
Classifier: Programming Language :: Python :: 3.13
Classifier: Programming Language :: Python :: 3.14
Classifier: Topic :: Software Development
Classifier: Topic :: Software Development :: Documentation
Classifier: Topic :: Utilities
Provides-Extra: ansible-core
Requires-Dist: Jinja2 (==3.1.6)
Requires-Dist: ansible-core (==2.16.15) ; extra == "ansible-core"
Requires-Dist: anyconfig (==0.14.0)
Requires-Dist: appdirs (==1.4.4)
Requires-Dist: colorama (==0.4.6)
Requires-Dist: dynaconf (==3.2.12)
Requires-Dist: gitpython (==3.1.46)
Requires-Dist: pathspec (==1.0.3)
Requires-Dist: ruamel.yaml (==0.19.1)
Requires-Dist: structlog (==25.5.0)
Project-URL: Documentation, https://ansible-doctor.geekdocs.de/
Project-URL: Homepage, https://ansible-doctor.geekdocs.de/
Project-URL: Repository, https://github.com/thegeeklab/ansible-doctor/
